onebeans/Test1.py
onebeans/Test2.py
onebeans-0.0.0.2.dist-info/METADATA
onebeans-0.0.0.2.dist-info/WHEEL
onebeans-0.0.0.2.dist-info/top_level.txt
onebeans-0.0.0.2.dist-info/RECORD
