Metadata-Version: 2.1
Name: onebeans
Version: 0.0.0.2
Summary: My First Test Package
Home-page: https://blog.naver.com/daltakin
Author: Wonbin Choi
Author-email: daltakin@naver.com
License: MIT
Platform: UNKNOWN
Requires-Python: >=3
